LICENSE
README.md
setup.py
gosundpy/__init__.py
gosundpy/device.py
gosundpy/exceptions.py
gosundpy/gosund.py
gosundpy/utils.py
gosundpy/version.py
gosundpy.egg-info/PKG-INFO
gosundpy.egg-info/SOURCES.txt
gosundpy.egg-info/dependency_links.txt
gosundpy.egg-info/requires.txt
gosundpy.egg-info/top_level.txt